cloud_compose_ecs-0.1.3-py2.7-nspkg.pth
cloud_compose_ecs-0.1.3.dist-info/DESCRIPTION.rst
cloud_compose_ecs-0.1.3.dist-info/METADATA
cloud_compose_ecs-0.1.3.dist-info/RECORD
cloud_compose_ecs-0.1.3.dist-info/WHEEL
cloud_compose_ecs-0.1.3.dist-info/metadata.json
cloud_compose_ecs-0.1.3.dist-info/namespace_packages.txt
cloud_compose_ecs-0.1.3.dist-info/top_level.txt
cloudcompose/ecs/__init__.py
cloudcompose/ecs/controller.py
cloudcompose/ecs/workflow.py
cloudcompose/ecs/commands/__init__.py
cloudcompose/ecs/commands/cli.py
