Metadata-Version: 2.0
Name: cloud-compose-ecs
Version: 0.1.3
Summary: ECS plugin for cloud-compose
Home-page: https://github.com/cloud-compose/cloud-compose-ecs
Author: WaPo platform tools team
Author-email: opensource@washingtonpost.com
License: UNKNOWN
Download-URL: https://github.com/cloud-compose/cloud-compose-ecs/tarball/v0.1.0
Keywords: ecs,cloud,compose,aws
Platform: UNKNOWN
Requires-Dist: click (>=6.6)
Requires-Dist: boto3 (>=1.3.1)
Requires-Dist: cloud-compose (>=0.4.0)
Requires-Dist: cloud-compose-cluster (>=0.14.0)
